polarisrag/__init__.py
polarisrag/base.py
polarisrag/const.py
polarisrag/db/__init__.py
polarisrag/db/milvus_db.py
polarisrag/embedding.py
polarisrag/factory.py
polarisrag/llm.py
polarisrag/model_mapping.py
polarisrag/polarisrag.py
polarisrag/prompt.py
polarisrag/tools.py
polarisrag/utils.py
polarisrag/vector_database.py
polarisrag-0.0.1.dist-info/LICENSE
polarisrag-0.0.1.dist-info/METADATA
polarisrag-0.0.1.dist-info/WHEEL
polarisrag-0.0.1.dist-info/RECORD
