Metadata-Version: 2.1
Name: polarisrag
Version: 0.0.1
Summary: PolarisRAG: Fast and Easy Retrieval-Augmented Generation
Author: SyJarvis
Author-email: 1755115828@qq.com
Requires-Python: >=3.10,<4.0
Classifier: Programming Language :: Python :: 3
Classifier: Programming Language :: Python :: 3.10
Classifier: Programming Language :: Python :: 3.11
Classifier: Programming Language :: Python :: 3.12
Classifier: Programming Language :: Python :: 3.13
